quad_torch/__init__.py
quad_torch/quad.py
quad_torch-0.4.5.dist-info/licenses/LICENSE
quad_torch-0.4.5.dist-info/WHEEL
quad_torch-0.4.5.dist-info/METADATA
quad_torch-0.4.5.dist-info/RECORD
